geode_simplex/__init__.py
geode_simplex/__init__.pyi
geode_simplex/brep_simplex.py
geode_simplex/brep_simplex.pyi
geode_simplex/metric_simplex.py
geode_simplex/metric_simplex.pyi
geode_simplex/py.typed
geode_simplex/section_simplex.py
geode_simplex/section_simplex.pyi
geode_simplex/lib64/__init__.pyi
geode_simplex/lib64/geode_simplex_py_brep.cpython-310-x86_64-linux-gnu.so
geode_simplex/lib64/geode_simplex_py_brep.pyi
geode_simplex/lib64/geode_simplex_py_metric.cpython-310-x86_64-linux-gnu.so
geode_simplex/lib64/geode_simplex_py_metric.pyi
geode_simplex/lib64/geode_simplex_py_section.cpython-310-x86_64-linux-gnu.so
geode_simplex/lib64/geode_simplex_py_section.pyi
geode_simplex/lib64/libGeode-Simplex_brep.so
geode_simplex/lib64/libGeode-Simplex_core.so
geode_simplex/lib64/libGeode-Simplex_corner.so
geode_simplex/lib64/libGeode-Simplex_line2d.so
geode_simplex/lib64/libGeode-Simplex_line3d.so
geode_simplex/lib64/libGeode-Simplex_line_common.so
geode_simplex/lib64/libGeode-Simplex_metric.so
geode_simplex/lib64/libGeode-Simplex_section.so
geode_simplex/lib64/libGeode-Simplex_solid.so
geode_simplex/lib64/libGeode-Simplex_surface2d.so
geode_simplex/lib64/libGeode-Simplex_surface3d.so
geode_simplex/lib64/libGeode-Simplex_surface_common.so
geode_simplex-10.0.4.dist-info/METADATA
geode_simplex-10.0.4.dist-info/WHEEL
geode_simplex-10.0.4.dist-info/top_level.txt
geode_simplex-10.0.4.dist-info/RECORD
